nanopy_bank/__init__.py
nanopy_bank/app.py
nanopy_bank/cli.py
nanopy_bank/api/__init__.py
nanopy_bank/api/server.py
nanopy_bank/core/__init__.py
nanopy_bank/core/audit.py
nanopy_bank/core/auth.py
nanopy_bank/core/bank.py
nanopy_bank/core/beneficiary.py
nanopy_bank/core/branch.py
nanopy_bank/core/fees.py
nanopy_bank/core/holding.py
nanopy_bank/core/models.py
nanopy_bank/core/products.py
nanopy_bank/data/__init__.py
nanopy_bank/data/demo.py
nanopy_bank/documents/__init__.py
nanopy_bank/documents/statement.py
nanopy_bank/sepa/__init__.py
nanopy_bank/sepa/sepa.py
nanopy_bank/storage/__init__.py
nanopy_bank/storage/json_storage.py
nanopy_bank/storage/sqlite_storage.py
nanopy_bank/ui/__init__.py
nanopy_bank/ui/pages.py
nanopy_bank/ui/pages/__init__.py
nanopy_bank/ui/pages/accounts.py
nanopy_bank/ui/pages/advisor.py
nanopy_bank/ui/pages/audit.py
nanopy_bank/ui/pages/beneficiaries.py
nanopy_bank/ui/pages/branches.py
nanopy_bank/ui/pages/cards.py
nanopy_bank/ui/pages/common.py
nanopy_bank/ui/pages/dashboard.py
nanopy_bank/ui/pages/fees.py
nanopy_bank/ui/pages/holding.py
nanopy_bank/ui/pages/loans.py
nanopy_bank/ui/pages/login.py
nanopy_bank/ui/pages/sepa.py
nanopy_bank/ui/pages/settings.py
nanopy_bank/ui/pages/transfers.py
nanopy_bank-1.0.8.dist-info/METADATA
nanopy_bank-1.0.8.dist-info/WHEEL
nanopy_bank-1.0.8.dist-info/entry_points.txt
nanopy_bank-1.0.8.dist-info/top_level.txt
nanopy_bank-1.0.8.dist-info/RECORD
