Metadata-Version: 2.4
Name: nanopy-bank
Version: 1.0.8
Summary: Online Banking System with Streamlit UI and SEPA XML support
Home-page: https://github.com/Web3-League/nanopy-bank
Author: NanoPy Team
Author-email: dev@nanopy.chain
Keywords: banking sepa xml iso20022 streamlit fintech
Classifier: Development Status :: 4 - Beta
Classifier: Intended Audience :: Developers
Classifier: License :: OSI Approved :: MIT License
Classifier: Programming Language :: Python :: 3
Classifier: Programming Language :: Python :: 3.10
Classifier: Programming Language :: Python :: 3.11
Classifier: Programming Language :: Python :: 3.12
Requires-Python: >=3.8
Requires-Dist: streamlit>=1.28.0
Requires-Dist: streamlit-shadcn-ui>=0.1.0
Requires-Dist: streamlit-extras>=0.3.0
Requires-Dist: streamlit-option-menu>=0.3.0
Requires-Dist: lxml>=4.9.0
Requires-Dist: pydantic>=2.0.0
Requires-Dist: sqlalchemy>=2.0.0
Requires-Dist: aiohttp>=3.8.0
Requires-Dist: python-dateutil>=2.8.0
Requires-Dist: schwifty>=2023.0.0
Requires-Dist: reportlab>=4.0.0
Requires-Dist: qrcode>=7.4.0
Requires-Dist: pillow>=10.0.0
Requires-Dist: click>=8.0.0
Dynamic: author
Dynamic: author-email
Dynamic: classifier
Dynamic: description
Dynamic: description-content-type
Dynamic: home-page
Dynamic: keywords
Dynamic: requires-dist
Dynamic: requires-python
Dynamic: summary
